inkscape_layer_utils/__init__.py
inkscape_layer_utils/__main__.py
inkscape_layer_utils/_version.py
inkscape_layer_utils/image.py
inkscape_layer_utils/main.py
inkscape_layer_utils/py.typed
tests/__init__.py
tests/image_test_case.py
tests/test_image_coloring.py
tests/test_image_layer_extraction.py
inkscape_layer_utils-0.7.0.dist-info/LICENSE
inkscape_layer_utils-0.7.0.dist-info/METADATA
inkscape_layer_utils-0.7.0.dist-info/WHEEL
inkscape_layer_utils-0.7.0.dist-info/entry_points.txt
inkscape_layer_utils-0.7.0.dist-info/top_level.txt
inkscape_layer_utils-0.7.0.dist-info/RECORD
