Metadata-Version: 2.1
Name: inkscape_layer_utils
Version: 0.7.0
Summary: Simple library to extract and manipulate layers in inkscape SVGs
Home-page: https://github.com/twyleg/inkscape_layer_utils
Author: Torsten Wylegala
Author-email: mail@twyleg.de
License: GPL 3.0
Keywords: inkscape svg layer utilities
License-File: LICENSE
Requires-Dist: simple-python-app >=0.4.0
